openpeerpower/.gitattributes
openpeerpower/__init__.py
openpeerpower/__main__.py
openpeerpower/bootstrap.py
openpeerpower/config.py
openpeerpower/config_entries.py
openpeerpower/const.py
openpeerpower/core.py
openpeerpower/data_entry_flow.py
openpeerpower/exceptions.py
openpeerpower/loader.py
openpeerpower/package_constraints.txt
openpeerpower/requirements.py
openpeerpower/setup.py
openpeerpower/auth/__init__.py
openpeerpower/auth/auth_store.py
openpeerpower/auth/const.py
openpeerpower/auth/models.py
openpeerpower/auth/util.py
openpeerpower/auth/mfa_modules/__init__.py
openpeerpower/auth/mfa_modules/insecure_example.py
openpeerpower/auth/mfa_modules/notify.py
openpeerpower/auth/mfa_modules/totp.py
openpeerpower/auth/permissions/__init__.py
openpeerpower/auth/permissions/const.py
openpeerpower/auth/permissions/entities.py
openpeerpower/auth/permissions/merge.py
openpeerpower/auth/permissions/models.py
openpeerpower/auth/permissions/system_policies.py
openpeerpower/auth/permissions/types.py
openpeerpower/auth/permissions/util.py
openpeerpower/auth/providers/__init__.py
openpeerpower/auth/providers/command_line.py
openpeerpower/auth/providers/insecure_example.py
openpeerpower/auth/providers/legacy_api_password.py
openpeerpower/auth/providers/openpeerpower.py
openpeerpower/auth/providers/trusted_networks.py
openpeerpower/components/__init__.py
openpeerpower/components/alarm_control_panel/__init__.py
openpeerpower/components/alarm_control_panel/const.py
openpeerpower/components/alarm_control_panel/device_action.py
openpeerpower/components/alarm_control_panel/device_trigger.py
openpeerpower/components/alarm_control_panel/manifest.json
openpeerpower/components/alarm_control_panel/reproduce_state.py
openpeerpower/components/alarm_control_panel/services.yaml
openpeerpower/components/alarm_control_panel/strings.json
openpeerpower/components/alert/__init__.py
openpeerpower/components/alert/manifest.json
openpeerpower/components/alert/services.yaml
openpeerpower-0.1.2.dist-info/LICENSE.md
openpeerpower-0.1.2.dist-info/METADATA
openpeerpower-0.1.2.dist-info/WHEEL
openpeerpower-0.1.2.dist-info/entry_points.txt
openpeerpower-0.1.2.dist-info/top_level.txt
openpeerpower-0.1.2.dist-info/RECORD
