Metadata-Version: 2.1
Name: openpeerpower
Version: 0.1.2
Summary: Open-source power management platform running on Python 3.
Home-page: https://OpenPeerPower.io/
Author: Paul Caston
Author-email: paul@caston.id.au
License: Apache License 2.0
Project-URL: Bug Reports, https://github.com/OpenPeerPower/Open-Peer-Power/issues
Keywords: power,management
Platform: any
Classifier: Development Status :: 3 - Alpha
Classifier: Intended Audience :: End Users/Desktop
Classifier: Intended Audience :: Developers
Classifier: License :: OSI Approved :: Apache Software License
Classifier: Operating System :: OS Independent
Classifier: Programming Language :: Python :: 3.7
Requires-Python: >=3.7.0
Requires-Dist: aiohttp (==3.6.1)
Requires-Dist: astral (==1.10.1)
Requires-Dist: async-timeout (==3.0.1)
Requires-Dist: attrs (==19.3.0)
Requires-Dist: bcrypt (==3.1.7)
Requires-Dist: certifi (>=2019.11.28)
Requires-Dist: importlib-metadata (==0.23)
Requires-Dist: jinja2 (>=2.10.3)
Requires-Dist: PyJWT (==1.7.1)
Requires-Dist: cryptography (==2.8)
Requires-Dist: pip (>=8.0.3)
Requires-Dist: python-slugify (==4.0.0)
Requires-Dist: pytz (>=2019.03)
Requires-Dist: pyyaml (==5.2.0)
Requires-Dist: requests (==2.22.0)
Requires-Dist: ruamel.yaml (==0.15.100)
Requires-Dist: voluptuous (==0.11.7)
Requires-Dist: voluptuous-serialize (==2.3.0)
